httpie_aws_authv4.py
httpie_aws_authv4-0.3.0.dist-info/LICENSE.md
httpie_aws_authv4-0.3.0.dist-info/METADATA
httpie_aws_authv4-0.3.0.dist-info/WHEEL
httpie_aws_authv4-0.3.0.dist-info/entry_points.txt
httpie_aws_authv4-0.3.0.dist-info/top_level.txt
httpie_aws_authv4-0.3.0.dist-info/RECORD
