Metadata-Version: 2.1
Name: httpie-aws-authv4
Version: 0.3.0
Summary: AWS auth v4 plugin for HTTPie.
Home-page: https://github.com/aidan-/httpie-aws-authv4
Download-URL: https://github.com/aidan-/httpie-aws-authv4
Author: Aidan Rowe
Author-email: aidanrowe@gmail.com
License: MIT
Platform: UNKNOWN
Classifier: Development Status :: 5 - Production/Stable
Classifier: Programming Language :: Python
Classifier: Programming Language :: Python :: 3
Classifier: Programming Language :: Python :: 3.4
Classifier: Programming Language :: Python :: 3.5
Classifier: Programming Language :: Python :: 3.6
Classifier: Programming Language :: Python :: 3.7
Classifier: Environment :: Plugins
Classifier: License :: OSI Approved :: BSD License
Classifier: Topic :: Internet :: WWW/HTTP
Classifier: Topic :: Utilities
License-File: LICENSE.md
Requires-Dist: httpie (>=1.0.0)
Requires-Dist: aws-requests-auth (>=0.4.0)
Requires-Dist: boto3 (>=1.9.0)
Requires-Dist: urllib3
